yt_dlp_plugins/extractor/ytse.py
yt_dlp_plugins/extractor/_ytse/__init__.py
yt_dlp_plugins/extractor/_ytse/ump.py
yt_dlp_plugins/extractor/_ytse/downloader/__init__.py
yt_dlp_plugins/extractor/_ytse/downloader/sabr.py
yt_dlp_plugins/extractor/_ytse/downloader/ump.py
yt_dlp_plugins/extractor/_ytse/protos/__init__.py
yt_dlp_plugins/extractor/_ytse/protos/_allowed_cached_formats.py
yt_dlp_plugins/extractor/_ytse/protos/_buffered_range.py
yt_dlp_plugins/extractor/_ytse/protos/_client_abr_state.py
yt_dlp_plugins/extractor/_ytse/protos/_format_id.py
yt_dlp_plugins/extractor/_ytse/protos/_format_initialization_metadata.py
yt_dlp_plugins/extractor/_ytse/protos/_live_metadata.py
yt_dlp_plugins/extractor/_ytse/protos/_media_capabilities.py
yt_dlp_plugins/extractor/_ytse/protos/_media_header.py
yt_dlp_plugins/extractor/_ytse/protos/_next_request_policy.py
yt_dlp_plugins/extractor/_ytse/protos/_playback_cookie.py
yt_dlp_plugins/extractor/_ytse/protos/_playback_start_policy.py
yt_dlp_plugins/extractor/_ytse/protos/_prewarm_connection.py
yt_dlp_plugins/extractor/_ytse/protos/_request_cancellation_policy.py
yt_dlp_plugins/extractor/_ytse/protos/_sabr_error.py
yt_dlp_plugins/extractor/_ytse/protos/_sabr_redirect.py
yt_dlp_plugins/extractor/_ytse/protos/_sabr_seek.py
yt_dlp_plugins/extractor/_ytse/protos/_selectable_formats.py
yt_dlp_plugins/extractor/_ytse/protos/_stream_protection_status.py
yt_dlp_plugins/extractor/_ytse/protos/_streamer_context.py
yt_dlp_plugins/extractor/_ytse/protos/_time_range.py
yt_dlp_plugins/extractor/_ytse/protos/_video_playback_abr_request.py
yt_dlp_ytse-0.4.1.dist-info/METADATA
yt_dlp_ytse-0.4.1.dist-info/WHEEL
yt_dlp_ytse-0.4.1.dist-info/licenses/LICENSE
yt_dlp_ytse-0.4.1.dist-info/RECORD
