Metadata-Version: 2.4
Name: yt-dlp-ytse
Version: 0.4.1
Author-email: coletdjnz <coletdjnz@protonmail.com>
License: MIT License
License-File: LICENSE
Keywords: yt-dlp,yt-dlp-plugin
Requires-Python: >=3.8
Requires-Dist: protobug
